avtomatika_worker/__init__.py
avtomatika_worker/client.py
avtomatika_worker/config.py
avtomatika_worker/constants.py
avtomatika_worker/py.typed
avtomatika_worker/s3.py
avtomatika_worker/task_files.py
avtomatika_worker/types.py
avtomatika_worker/worker.py
avtomatika_worker-1.0b3.dist-info/licenses/LICENSE
avtomatika_worker-1.0b3.dist-info/METADATA
avtomatika_worker-1.0b3.dist-info/WHEEL
avtomatika_worker-1.0b3.dist-info/top_level.txt
avtomatika_worker-1.0b3.dist-info/RECORD
