Metadata-Version: 2.4
Name: avtomatika-worker
Version: 1.0b3
Summary: Worker SDK for the Avtomatika orchestrator.
Project-URL: Homepage, https://github.com/avtomatika-ai/avtomatika-worker
Project-URL: Bug Tracker, https://github.com/avtomatika-ai/avtomatika-worker/issues
Classifier: Development Status :: 4 - Beta
Classifier: Programming Language :: Python :: 3
Classifier: License :: OSI Approved :: MIT License
Classifier: Operating System :: OS Independent
Requires-Python: >=3.11
License-File: LICENSE
Requires-Dist: aiohttp~=3.13.2
Requires-Dist: python-json-logger~=4.0.0
Requires-Dist: obstore>=0.1
Requires-Dist: aiofiles~=25.1.0
Provides-Extra: test
Requires-Dist: pytest; extra == "test"
Requires-Dist: pytest-asyncio; extra == "test"
Requires-Dist: aioresponses; extra == "test"
Requires-Dist: pytest-mock; extra == "test"
Requires-Dist: pydantic; extra == "test"
Requires-Dist: types-aiofiles; extra == "test"
Provides-Extra: pydantic
Requires-Dist: pydantic; extra == "pydantic"
Dynamic: license-file
